iflow/__init__.py
iflow/integration/__init__.py
iflow/integration/couplings.py
iflow/integration/divergences.py
iflow/integration/integrator.py
iflow/integration/sinkhorn.py
iflow/splines/__init__.py
iflow/splines/cubic.py
iflow/splines/linear.py
iflow/splines/quadratic.py
iflow/splines/rational_quadratic.py
iflow/splines/spline.py
tests/__init__.py
tests/couplings_test.py
tests/divergences_test.py
tests/integration_test.py
tests/integrator_test.py
tests/spline_test.py
iflow-1.0.1.dist-info/LICENSE
iflow-1.0.1.dist-info/METADATA
iflow-1.0.1.dist-info/WHEEL
iflow-1.0.1.dist-info/top_level.txt
iflow-1.0.1.dist-info/RECORD
