Metadata-Version: 2.1
Name: iflow
Version: 1.0.1
Summary: Monte-Carlo Integration using Neural Networks
Home-page: https://gitlab.com/isaacson/nicephasespace
Author: Christina Gao,             Joshua Isaacson,             Claudius Krause
License: UNKNOWN
Platform: UNKNOWN
Classifier: Development Status :: 3 - Alpha
Classifier: Programming Language :: Python :: 2.7
Classifier: Programming Language :: Python :: 3
Requires-Python: >=2.7, !=3.0.*, !=3.1.*, !=3.2.*, <4
Requires-Dist: numpy
Requires-Dist: tensorflow (>=2.0)
Requires-Dist: tensorflow-probability (>=0.8.0)
Provides-Extra: test
Requires-Dist: pytest ; extra == 'test'
Requires-Dist: coverage ; extra == 'test'
Requires-Dist: pytest-cov ; extra == 'test'
